limit_reader.py
test_limit_reader.py
limit_reader-0.1.0.dist-info/LICENSE.txt
limit_reader-0.1.0.dist-info/WHEEL
limit_reader-0.1.0.dist-info/METADATA
limit_reader-0.1.0.dist-info/RECORD
